amis/__init__.py
amis/components.py
amis/constants.py
amis/templates/app.jinja2
amis/templates/page.jinja2
amis/types.py
amis_python-1.0.8.post2.dist-info/LICENSE
amis_python-1.0.8.post2.dist-info/METADATA
amis_python-1.0.8.post2.dist-info/WHEEL
amis_python-1.0.8.post2.dist-info/RECORD
