Metadata-Version: 2.1
Name: amis-python
Version: 1.0.8.post2
Summary: 基于百度amis前端框架的python pydantic模型封装。
Home-page: https://github.com/CMHopeSunshine/amis-py
License: Apache-2.0
Keywords: amis
Author: 惜月
Author-email: 277073121@qq.com
Requires-Python: >=3.7,<4.0
Classifier: License :: OSI Approved :: Apache Software License
Classifier: Programming Language :: Python :: 3
Classifier: Programming Language :: Python :: 3.7
Classifier: Programming Language :: Python :: 3.8
Classifier: Programming Language :: Python :: 3.9
Classifier: Programming Language :: Python :: 3.10
Classifier: Programming Language :: Python :: 3.11
Requires-Dist: jinja2 (>=3.1.2,<4.0.0)
Requires-Dist: pydantic (>=1.9.2,<2.0.0)
Project-URL: Documentation, https://github.com/CMHopeSunshine/amis-py#readme
Project-URL: Repository, https://github.com/CMHopeSunshine/amis-py
